mybuildbackend/__init__.py
mybuildbackend/build_meta.py
mybuildbackend-0.0.7.dist-info/METADATA
mybuildbackend-0.0.7.dist-info/WHEEL
mybuildbackend-0.0.7.dist-info/top_level.txt
mybuildbackend-0.0.7.dist-info/RECORD
