Metadata-Version: 2.1
Name: mybuildbackend
Version: 0.0.7
Summary: UNKNOWN
License: UNKNOWN
Platform: UNKNOWN
Requires-Python: >=3.7
Requires-Dist: setuptools
Requires-Dist: importlib-metadata ; python_version < "3.8"
